Compiled from "ClamAV.java"
public class io.sensesecure.clamav4j.ClamAV {
  private java.net.InetSocketAddress address;

  private int timeout;

  protected static final byte[] INSTREAM;

  protected static final java.util.regex.Pattern FOUND;

  protected static final java.lang.String OK;

  protected static final int CHUNK;

  protected static final byte[] PING;

  protected static final java.lang.String PONG;

  protected static final byte[] VERSION;

  protected static final int defaultTimeout;

  protected static final int defaultPort;

  protected static final java.lang.String defaultHost;

  public io.sensesecure.clamav4j.ClamAV(java.net.InetSocketAddress, int);
    Code:
       0: aload_0
       1: invokespecial #1                  // Method java/lang/Object."<init>":()V
       4: aload_0
       5: aload_1
       6: putfield      #2                  // Field address:Ljava/net/InetSocketAddress;
       9: aload_0
      10: iload_2
      11: putfield      #3                  // Field timeout:I
      14: return

  public java.net.InetSocketAddress getAddress();
    Code:
       0: aload_0
       1: getfield      #2                  // Field address:Ljava/net/InetSocketAddress;
       4: areturn

  public void setAddress(java.net.InetSocketAddress);
    Code:
       0: aload_0
       1: aload_1
       2: putfield      #2                  // Field address:Ljava/net/InetSocketAddress;
       5: return

  public int getTimeout();
    Code:
       0: aload_0
       1: getfield      #3                  // Field timeout:I
       4: ireturn

  public void setTimeout(int);
    Code:
       0: aload_0
       1: iload_1
       2: putfield      #3                  // Field timeout:I
       5: return

  public java.lang.String scan(java.nio.channels.FileChannel) throws java.io.IOException, io.sensesecure.clamav4j.ClamAVException;
    Code:
       0: aload_1
       1: aload_0
       2: getfield      #2                  // Field address:Ljava/net/InetSocketAddress;
       5: aload_0
       6: getfield      #3                  // Field timeout:I
       9: invokestatic  #4                  // Method scan:(Ljava/nio/channels/FileChannel;Ljava/net/InetSocketAddress;I)Ljava/lang/String;
      12: areturn

  public java.lang.String scan(java.io.InputStream) throws java.io.IOException, io.sensesecure.clamav4j.ClamAVException;
    Code:
       0: aload_1
       1: aload_0
       2: getfield      #2                  // Field address:Ljava/net/InetSocketAddress;
       5: aload_0
       6: getfield      #3                  // Field timeout:I
       9: invokestatic  #5                  // Method scan:(Ljava/io/InputStream;Ljava/net/InetSocketAddress;I)Ljava/lang/String;
      12: areturn

  public boolean ping();
    Code:
       0: aload_0
       1: getfield      #2                  // Field address:Ljava/net/InetSocketAddress;
       4: aload_0
       5: getfield      #3                  // Field timeout:I
       8: invokestatic  #6                  // Method ping:(Ljava/net/InetSocketAddress;I)Z
      11: ireturn

  public static boolean ping(java.net.InetSocketAddress, int);
    Code:
       0: aload_0
       1: invokestatic  #7                  // Method java/nio/channels/SocketChannel.open:(Ljava/net/SocketAddress;)Ljava/nio/channels/SocketChannel;
       4: astore_2
       5: aconst_null
       6: astore_3
       7: aload_2
       8: getstatic     #8                  // Field PING:[B
      11: invokestatic  #9                  // Method java/nio/ByteBuffer.wrap:([B)Ljava/nio/ByteBuffer;
      14: invokevirtual #10                 // Method java/nio/channels/SocketChannel.write:(Ljava/nio/ByteBuffer;)I
      17: pop
      18: aload_2
      19: invokevirtual #11                 // Method java/nio/channels/SocketChannel.socket:()Ljava/net/Socket;
      22: iload_1
      23: invokevirtual #12                 // Method java/net/Socket.setSoTimeout:(I)V
      26: sipush        1024
      29: invokestatic  #13                 // Method java/nio/ByteBuffer.allocate:(I)Ljava/nio/ByteBuffer;
      32: astore        4
      34: aload_2
      35: aload         4
      37: invokevirtual #14                 // Method java/nio/channels/SocketChannel.read:(Ljava/nio/ByteBuffer;)I
      40: pop
      41: new           #15                 // class java/lang/String
      44: dup
      45: aload         4
      47: invokevirtual #16                 // Method java/nio/ByteBuffer.array:()[B
      50: invokespecial #17                 // Method java/lang/String."<init>":([B)V
      53: astore        5
      55: aload         5
      57: iconst_0
      58: aload         5
      60: iconst_0
      61: invokevirtual #18                 // Method java/lang/String.indexOf:(I)I
      64: invokevirtual #19                 // Method java/lang/String.substring:(II)Ljava/lang/String;
      67: astore        5
      69: ldc           #21                 // String PONG
      71: aload         5
      73: invokevirtual #22                 // Method java/lang/String.equals:(Ljava/lang/Object;)Z
      76: ifeq          115
      79: iconst_1
      80: istore        6
      82: aload_2
      83: ifnull        112
      86: aload_3
      87: ifnull        108
      90: aload_2
      91: invokevirtual #23                 // Method java/nio/channels/SocketChannel.close:()V
      94: goto          112
      97: astore        7
      99: aload_3
     100: aload         7
     102: invokevirtual #25                 // Method java/lang/Throwable.addSuppressed:(Ljava/lang/Throwable;)V
     105: goto          112
     108: aload_2
     109: invokevirtual #23                 // Method java/nio/channels/SocketChannel.close:()V
     112: iload         6
     114: ireturn
     115: aload_2
     116: ifnull        191
     119: aload_3
     120: ifnull        141
     123: aload_2
     124: invokevirtual #23                 // Method java/nio/channels/SocketChannel.close:()V
     127: goto          191
     130: astore        4
     132: aload_3
     133: aload         4
     135: invokevirtual #25                 // Method java/lang/Throwable.addSuppressed:(Ljava/lang/Throwable;)V
     138: goto          191
     141: aload_2
     142: invokevirtual #23                 // Method java/nio/channels/SocketChannel.close:()V
     145: goto          191
     148: astore        4
     150: aload         4
     152: astore_3
     153: aload         4
     155: athrow
     156: astore        8
     158: aload_2
     159: ifnull        188
     162: aload_3
     163: ifnull        184
     166: aload_2
     167: invokevirtual #23                 // Method java/nio/channels/SocketChannel.close:()V
     170: goto          188
     173: astore        9
     175: aload_3
     176: aload         9
     178: invokevirtual #25                 // Method java/lang/Throwable.addSuppressed:(Ljava/lang/Throwable;)V
     181: goto          188
     184: aload_2
     185: invokevirtual #23                 // Method java/nio/channels/SocketChannel.close:()V
     188: aload         8
     190: athrow
     191: goto          211
     194: astore_2
     195: ldc           #20                 // class io/sensesecure/clamav4j/ClamAV
     197: invokevirtual #27                 // Method java/lang/Class.getName:()Ljava/lang/String;
     200: invokestatic  #28                 // Method java/util/logging/Logger.getLogger:(Ljava/lang/String;)Ljava/util/logging/Logger;
     203: getstatic     #29                 // Field java/util/logging/Level.SEVERE:Ljava/util/logging/Level;
     206: aconst_null
     207: aload_2
     208: invokevirtual #30                 // Method java/util/logging/Logger.log:(Ljava/util/logging/Level;Ljava/lang/String;Ljava/lang/Throwable;)V
     211: iconst_0
     212: ireturn
    Exception table:
       from    to  target type
          90    94    97   Class java/lang/Throwable
         123   127   130   Class java/lang/Throwable
           7    82   148   Class java/lang/Throwable
           7    82   156   any
         166   170   173   Class java/lang/Throwable
         148   158   156   any
           0   112   194   Class java/io/IOException
         115   191   194   Class java/io/IOException

  public static java.lang.String scan(java.nio.channels.FileChannel, java.net.InetSocketAddress, int) throws java.io.IOException, io.sensesecure.clamav4j.ClamAVException;
    Code:
       0: aload_1
       1: invokestatic  #7                  // Method java/nio/channels/SocketChannel.open:(Ljava/net/SocketAddress;)Ljava/nio/channels/SocketChannel;
       4: astore_3
       5: aconst_null
       6: astore        4
       8: aload_3
       9: getstatic     #31                 // Field INSTREAM:[B
      12: invokestatic  #9                  // Method java/nio/ByteBuffer.wrap:([B)Ljava/nio/ByteBuffer;
      15: invokevirtual #10                 // Method java/nio/channels/SocketChannel.write:(Ljava/nio/ByteBuffer;)I
      18: pop
      19: iconst_4
      20: invokestatic  #13                 // Method java/nio/ByteBuffer.allocate:(I)Ljava/nio/ByteBuffer;
      23: astore        5
      25: aload         5
      27: invokevirtual #32                 // Method java/nio/ByteBuffer.clear:()Ljava/nio/Buffer;
      30: pop
      31: aload         5
      33: aload_0
      34: invokevirtual #33                 // Method java/nio/channels/FileChannel.size:()J
      37: l2i
      38: invokevirtual #34                 // Method java/nio/ByteBuffer.putInt:(I)Ljava/nio/ByteBuffer;
      41: invokevirtual #35                 // Method java/nio/ByteBuffer.flip:()Ljava/nio/Buffer;
      44: pop
      45: aload_3
      46: aload         5
      48: invokevirtual #10                 // Method java/nio/channels/SocketChannel.write:(Ljava/nio/ByteBuffer;)I
      51: pop
      52: aload_0
      53: lconst_0
      54: aload_0
      55: invokevirtual #33                 // Method java/nio/channels/FileChannel.size:()J
      58: l2i
      59: i2l
      60: aload_3
      61: invokevirtual #36                 // Method java/nio/channels/FileChannel.transferTo:(JJLjava/nio/channels/WritableByteChannel;)J
      64: pop2
      65: aload         5
      67: invokevirtual #32                 // Method java/nio/ByteBuffer.clear:()Ljava/nio/Buffer;
      70: pop
      71: aload         5
      73: iconst_0
      74: invokevirtual #34                 // Method java/nio/ByteBuffer.putInt:(I)Ljava/nio/ByteBuffer;
      77: invokevirtual #35                 // Method java/nio/ByteBuffer.flip:()Ljava/nio/Buffer;
      80: pop
      81: aload_3
      82: aload         5
      84: invokevirtual #10                 // Method java/nio/channels/SocketChannel.write:(Ljava/nio/ByteBuffer;)I
      87: pop
      88: aload_3
      89: iload_2
      90: invokestatic  #37                 // Method scanResult:(Ljava/nio/channels/SocketChannel;I)Ljava/lang/String;
      93: astore        6
      95: aload_3
      96: ifnull        127
      99: aload         4
     101: ifnull        123
     104: aload_3
     105: invokevirtual #23                 // Method java/nio/channels/SocketChannel.close:()V
     108: goto          127
     111: astore        7
     113: aload         4
     115: aload         7
     117: invokevirtual #25                 // Method java/lang/Throwable.addSuppressed:(Ljava/lang/Throwable;)V
     120: goto          127
     123: aload_3
     124: invokevirtual #23                 // Method java/nio/channels/SocketChannel.close:()V
     127: aload         6
     129: areturn
     130: astore        5
     132: aload         5
     134: astore        4
     136: aload         5
     138: athrow
     139: astore        8
     141: aload_3
     142: ifnull        173
     145: aload         4
     147: ifnull        169
     150: aload_3
     151: invokevirtual #23                 // Method java/nio/channels/SocketChannel.close:()V
     154: goto          173
     157: astore        9
     159: aload         4
     161: aload         9
     163: invokevirtual #25                 // Method java/lang/Throwable.addSuppressed:(Ljava/lang/Throwable;)V
     166: goto          173
     169: aload_3
     170: invokevirtual #23                 // Method java/nio/channels/SocketChannel.close:()V
     173: aload         8
     175: athrow
    Exception table:
       from    to  target type
         104   108   111   Class java/lang/Throwable
           8    95   130   Class java/lang/Throwable
           8    95   139   any
         150   154   157   Class java/lang/Throwable
         130   141   139   any

  public static java.lang.String scan(java.io.InputStream, java.net.InetSocketAddress, int) throws java.io.IOException, io.sensesecure.clamav4j.ClamAVException;
    Code:
       0: aload_1
       1: invokestatic  #7                  // Method java/nio/channels/SocketChannel.open:(Ljava/net/SocketAddress;)Ljava/nio/channels/SocketChannel;
       4: astore_3
       5: aconst_null
       6: astore        4
       8: aload_3
       9: getstatic     #31                 // Field INSTREAM:[B
      12: invokestatic  #9                  // Method java/nio/ByteBuffer.wrap:([B)Ljava/nio/ByteBuffer;
      15: invokevirtual #10                 // Method java/nio/channels/SocketChannel.write:(Ljava/nio/ByteBuffer;)I
      18: pop
      19: iconst_4
      20: invokestatic  #13                 // Method java/nio/ByteBuffer.allocate:(I)Ljava/nio/ByteBuffer;
      23: astore        5
      25: sipush        4096
      28: newarray       byte
      30: astore        6
      32: sipush        4096
      35: istore        7
      37: iload         7
      39: sipush        4096
      42: if_icmpne     98
      45: aload_0
      46: aload         6
      48: invokevirtual #38                 // Method java/io/InputStream.read:([B)I
      51: istore        7
      53: iload         7
      55: ifle          37
      58: aload         5
      60: invokevirtual #32                 // Method java/nio/ByteBuffer.clear:()Ljava/nio/Buffer;
      63: pop
      64: aload         5
      66: iload         7
      68: invokevirtual #34                 // Method java/nio/ByteBuffer.putInt:(I)Ljava/nio/ByteBuffer;
      71: invokevirtual #35                 // Method java/nio/ByteBuffer.flip:()Ljava/nio/Buffer;
      74: pop
      75: aload_3
      76: aload         5
      78: invokevirtual #10                 // Method java/nio/channels/SocketChannel.write:(Ljava/nio/ByteBuffer;)I
      81: pop
      82: aload_3
      83: aload         6
      85: iconst_0
      86: iload         7
      88: invokestatic  #39                 // Method java/nio/ByteBuffer.wrap:([BII)Ljava/nio/ByteBuffer;
      91: invokevirtual #10                 // Method java/nio/channels/SocketChannel.write:(Ljava/nio/ByteBuffer;)I
      94: pop
      95: goto          37
      98: aload         5
     100: invokevirtual #32                 // Method java/nio/ByteBuffer.clear:()Ljava/nio/Buffer;
     103: pop
     104: aload         5
     106: iconst_0
     107: invokevirtual #34                 // Method java/nio/ByteBuffer.putInt:(I)Ljava/nio/ByteBuffer;
     110: invokevirtual #35                 // Method java/nio/ByteBuffer.flip:()Ljava/nio/Buffer;
     113: pop
     114: aload_3
     115: aload         5
     117: invokevirtual #10                 // Method java/nio/channels/SocketChannel.write:(Ljava/nio/ByteBuffer;)I
     120: pop
     121: aload_3
     122: iload_2
     123: invokestatic  #37                 // Method scanResult:(Ljava/nio/channels/SocketChannel;I)Ljava/lang/String;
     126: astore        8
     128: aload_3
     129: ifnull        160
     132: aload         4
     134: ifnull        156
     137: aload_3
     138: invokevirtual #23                 // Method java/nio/channels/SocketChannel.close:()V
     141: goto          160
     144: astore        9
     146: aload         4
     148: aload         9
     150: invokevirtual #25                 // Method java/lang/Throwable.addSuppressed:(Ljava/lang/Throwable;)V
     153: goto          160
     156: aload_3
     157: invokevirtual #23                 // Method java/nio/channels/SocketChannel.close:()V
     160: aload         8
     162: areturn
     163: astore        5
     165: aload         5
     167: astore        4
     169: aload         5
     171: athrow
     172: astore        10
     174: aload_3
     175: ifnull        206
     178: aload         4
     180: ifnull        202
     183: aload_3
     184: invokevirtual #23                 // Method java/nio/channels/SocketChannel.close:()V
     187: goto          206
     190: astore        11
     192: aload         4
     194: aload         11
     196: invokevirtual #25                 // Method java/lang/Throwable.addSuppressed:(Ljava/lang/Throwable;)V
     199: goto          206
     202: aload_3
     203: invokevirtual #23                 // Method java/nio/channels/SocketChannel.close:()V
     206: aload         10
     208: athrow
    Exception table:
       from    to  target type
         137   141   144   Class java/lang/Throwable
           8   128   163   Class java/lang/Throwable
           8   128   172   any
         183   187   190   Class java/lang/Throwable
         163   174   172   any

  private static java.lang.String scanResult(java.nio.channels.SocketChannel, int) throws java.io.IOException, io.sensesecure.clamav4j.ClamAVException;
    Code:
       0: aload_0
       1: invokevirtual #11                 // Method java/nio/channels/SocketChannel.socket:()Ljava/net/Socket;
       4: iload_1
       5: invokevirtual #12                 // Method java/net/Socket.setSoTimeout:(I)V
       8: sipush        1024
      11: invokestatic  #13                 // Method java/nio/ByteBuffer.allocate:(I)Ljava/nio/ByteBuffer;
      14: astore_2
      15: aload_0
      16: aload_2
      17: invokevirtual #14                 // Method java/nio/channels/SocketChannel.read:(Ljava/nio/ByteBuffer;)I
      20: pop
      21: new           #15                 // class java/lang/String
      24: dup
      25: aload_2
      26: invokevirtual #16                 // Method java/nio/ByteBuffer.array:()[B
      29: invokespecial #17                 // Method java/lang/String."<init>":([B)V
      32: astore_3
      33: aload_3
      34: iconst_0
      35: aload_3
      36: iconst_0
      37: invokevirtual #18                 // Method java/lang/String.indexOf:(I)I
      40: invokevirtual #19                 // Method java/lang/String.substring:(II)Ljava/lang/String;
      43: astore_3
      44: getstatic     #40                 // Field FOUND:Ljava/util/regex/Pattern;
      47: aload_3
      48: invokevirtual #41                 // Method java/util/regex/Pattern.matcher:(Ljava/lang/CharSequence;)Ljava/util/regex/Matcher;
      51: astore        4
      53: aload         4
      55: invokevirtual #42                 // Method java/util/regex/Matcher.matches:()Z
      58: ifeq          68
      61: aload         4
      63: iconst_1
      64: invokevirtual #43                 // Method java/util/regex/Matcher.group:(I)Ljava/lang/String;
      67: areturn
      68: ldc           #44                 // String stream: OK
      70: aload_3
      71: invokevirtual #22                 // Method java/lang/String.equals:(Ljava/lang/Object;)Z
      74: ifeq          80
      77: ldc           #45                 // String OK
      79: areturn
      80: new           #46                 // class io/sensesecure/clamav4j/ClamAVException
      83: dup
      84: aload_3
      85: invokespecial #47                 // Method io/sensesecure/clamav4j/ClamAVException."<init>":(Ljava/lang/String;)V
      88: athrow

  public io.sensesecure.clamav4j.ClamAVVersion getVersion();
    Code:
       0: aload_0
       1: getfield      #2                  // Field address:Ljava/net/InetSocketAddress;
       4: aload_0
       5: getfield      #3                  // Field timeout:I
       8: invokestatic  #48                 // Method getVersion:(Ljava/net/InetSocketAddress;I)Lio/sensesecure/clamav4j/ClamAVVersion;
      11: areturn

  public static io.sensesecure.clamav4j.ClamAVVersion getVersion(java.net.InetSocketAddress, int);
    Code:
       0: aload_0
       1: invokestatic  #7                  // Method java/nio/channels/SocketChannel.open:(Ljava/net/SocketAddress;)Ljava/nio/channels/SocketChannel;
       4: astore_2
       5: aconst_null
       6: astore_3
       7: aload_2
       8: getstatic     #49                 // Field VERSION:[B
      11: invokestatic  #9                  // Method java/nio/ByteBuffer.wrap:([B)Ljava/nio/ByteBuffer;
      14: invokevirtual #10                 // Method java/nio/channels/SocketChannel.write:(Ljava/nio/ByteBuffer;)I
      17: pop
      18: aload_2
      19: invokevirtual #11                 // Method java/nio/channels/SocketChannel.socket:()Ljava/net/Socket;
      22: iload_1
      23: invokevirtual #12                 // Method java/net/Socket.setSoTimeout:(I)V
      26: sipush        1024
      29: invokestatic  #13                 // Method java/nio/ByteBuffer.allocate:(I)Ljava/nio/ByteBuffer;
      32: astore        4
      34: aload_2
      35: aload         4
      37: invokevirtual #14                 // Method java/nio/channels/SocketChannel.read:(Ljava/nio/ByteBuffer;)I
      40: pop
      41: new           #15                 // class java/lang/String
      44: dup
      45: aload         4
      47: invokevirtual #16                 // Method java/nio/ByteBuffer.array:()[B
      50: invokespecial #17                 // Method java/lang/String."<init>":([B)V
      53: astore        5
      55: aload         5
      57: iconst_0
      58: aload         5
      60: iconst_0
      61: invokevirtual #18                 // Method java/lang/String.indexOf:(I)I
      64: invokevirtual #19                 // Method java/lang/String.substring:(II)Ljava/lang/String;
      67: astore        5
      69: new           #50                 // class io/sensesecure/clamav4j/ClamAVVersion
      72: dup
      73: aload         5
      75: invokespecial #51                 // Method io/sensesecure/clamav4j/ClamAVVersion."<init>":(Ljava/lang/String;)V
      78: astore        6
      80: aload_2
      81: ifnull        110
      84: aload_3
      85: ifnull        106
      88: aload_2
      89: invokevirtual #23                 // Method java/nio/channels/SocketChannel.close:()V
      92: goto          110
      95: astore        7
      97: aload_3
      98: aload         7
     100: invokevirtual #25                 // Method java/lang/Throwable.addSuppressed:(Ljava/lang/Throwable;)V
     103: goto          110
     106: aload_2
     107: invokevirtual #23                 // Method java/nio/channels/SocketChannel.close:()V
     110: aload         6
     112: areturn
     113: astore        4
     115: aload         4
     117: astore_3
     118: aload         4
     120: athrow
     121: astore        8
     123: aload_2
     124: ifnull        153
     127: aload_3
     128: ifnull        149
     131: aload_2
     132: invokevirtual #23                 // Method java/nio/channels/SocketChannel.close:()V
     135: goto          153
     138: astore        9
     140: aload_3
     141: aload         9
     143: invokevirtual #25                 // Method java/lang/Throwable.addSuppressed:(Ljava/lang/Throwable;)V
     146: goto          153
     149: aload_2
     150: invokevirtual #23                 // Method java/nio/channels/SocketChannel.close:()V
     153: aload         8
     155: athrow
     156: astore_2
     157: ldc           #20                 // class io/sensesecure/clamav4j/ClamAV
     159: invokevirtual #27                 // Method java/lang/Class.getName:()Ljava/lang/String;
     162: invokestatic  #28                 // Method java/util/logging/Logger.getLogger:(Ljava/lang/String;)Ljava/util/logging/Logger;
     165: getstatic     #29                 // Field java/util/logging/Level.SEVERE:Ljava/util/logging/Level;
     168: aconst_null
     169: aload_2
     170: invokevirtual #30                 // Method java/util/logging/Logger.log:(Ljava/util/logging/Level;Ljava/lang/String;Ljava/lang/Throwable;)V
     173: aconst_null
     174: areturn
    Exception table:
       from    to  target type
          88    92    95   Class java/lang/Throwable
           7    80   113   Class java/lang/Throwable
           7    80   121   any
         131   135   138   Class java/lang/Throwable
         113   123   121   any
           0   110   156   Class java/io/IOException
         113   156   156   Class java/io/IOException

  public static void main(java.lang.String[]);
    Code:
       0: aload_0
       1: arraylength
       2: ifne          14
       5: getstatic     #52                 // Field java/lang/System.out:Ljava/io/PrintStream;
       8: ldc           #53                 // String Usage: java program [--host <host>] [--port <port>] [--timeout <timeout>] [--channel] [--ping] [<file/directory>]
      10: invokevirtual #54                 // Method java/io/PrintStream.println:(Ljava/lang/String;)V
      13: return
      14: iconst_0
      15: istore_1
      16: sipush        3310
      19: istore_2
      20: ldc           #55                 // String localhost
      22: astore_3
      23: iconst_0
      24: istore        4
      26: iconst_0
      27: istore        5
      29: iconst_0
      30: istore        6
      32: iload         6
      34: aload_0
      35: arraylength
      36: iconst_1
      37: isub
      38: if_icmpge     200
      41: ldc           #56                 // String --host
      43: aload_0
      44: iload         6
      46: aaload
      47: invokevirtual #22                 // Method java/lang/String.equals:(Ljava/lang/Object;)Z
      50: ifeq          75
      53: iload         6
      55: iconst_1
      56: iadd
      57: aload_0
      58: arraylength
      59: iconst_1
      60: isub
      61: if_icmpge     75
      64: iinc          6, 1
      67: aload_0
      68: iload         6
      70: aaload
      71: astore_3
      72: goto          194
      75: ldc           #57                 // String --port
      77: aload_0
      78: iload         6
      80: aaload
      81: invokevirtual #22                 // Method java/lang/String.equals:(Ljava/lang/Object;)Z
      84: ifeq          112
      87: iload         6
      89: iconst_1
      90: iadd
      91: aload_0
      92: arraylength
      93: iconst_1
      94: isub
      95: if_icmpge     112
      98: iinc          6, 1
     101: aload_0
     102: iload         6
     104: aaload
     105: invokestatic  #58                 // Method java/lang/Integer.parseInt:(Ljava/lang/String;)I
     108: istore_2
     109: goto          194
     112: ldc           #59                 // String --timeout
     114: aload_0
     115: iload         6
     117: aaload
     118: invokevirtual #22                 // Method java/lang/String.equals:(Ljava/lang/Object;)Z
     121: ifeq          149
     124: iload         6
     126: iconst_1
     127: iadd
     128: aload_0
     129: arraylength
     130: iconst_1
     131: isub
     132: if_icmpge     149
     135: iinc          6, 1
     138: aload_0
     139: iload         6
     141: aaload
     142: invokestatic  #58                 // Method java/lang/Integer.parseInt:(Ljava/lang/String;)I
     145: istore_1
     146: goto          194
     149: ldc           #60                 // String --channel
     151: aload_0
     152: iload         6
     154: aaload
     155: invokevirtual #22                 // Method java/lang/String.equals:(Ljava/lang/Object;)Z
     158: ifeq          167
     161: iconst_1
     162: istore        4
     164: goto          194
     167: ldc           #61                 // String --ping
     169: aload_0
     170: iload         6
     172: aaload
     173: invokevirtual #22                 // Method java/lang/String.equals:(Ljava/lang/Object;)Z
     176: ifeq          185
     179: iconst_1
     180: istore        5
     182: goto          194
     185: getstatic     #52                 // Field java/lang/System.out:Ljava/io/PrintStream;
     188: ldc           #62                 // String Usage: java program [--host <host>] [--port <port>] [--timeout <timeout>] <file/directory>
     190: invokevirtual #54                 // Method java/io/PrintStream.println:(Ljava/lang/String;)V
     193: return
     194: iinc          6, 1
     197: goto          32
     200: new           #20                 // class io/sensesecure/clamav4j/ClamAV
     203: dup
     204: new           #63                 // class java/net/InetSocketAddress
     207: dup
     208: aload_3
     209: iload_2
     210: invokespecial #64                 // Method java/net/InetSocketAddress."<init>":(Ljava/lang/String;I)V
     213: iload_1
     214: invokespecial #65                 // Method "<init>":(Ljava/net/InetSocketAddress;I)V
     217: astore        6
     219: iload         5
     221: ifne          238
     224: ldc           #61                 // String --ping
     226: aload_0
     227: aload_0
     228: arraylength
     229: iconst_1
     230: isub
     231: aaload
     232: invokevirtual #22                 // Method java/lang/String.equals:(Ljava/lang/Object;)Z
     235: ifeq          288
     238: getstatic     #52                 // Field java/lang/System.out:Ljava/io/PrintStream;
     241: new           #66                 // class java/lang/StringBuilder
     244: dup
     245: invokespecial #67                 // Method java/lang/StringBuilder."<init>":()V
     248: aload         6
     250: invokevirtual #68                 // Method getAddress:()Ljava/net/InetSocketAddress;
     253: invokevirtual #69                 // Method java/lang/StringBuilder.append:(Ljava/lang/Object;)Ljava/lang/StringBuilder;
     256: ldc           #70                 // String :
     258: invokevirtual #71                 // Method java/lang/StringBuilder.append:(Ljava/lang/String;)Ljava/lang/StringBuilder;
     261: aload         6
     263: invokevirtual #72                 // Method ping:()Z
     266: ifeq          274
     269: ldc           #73                 // String ALIVE
     271: goto          276
     274: ldc           #74                 // String DOWN
     276: invokevirtual #71                 // Method java/lang/StringBuilder.append:(Ljava/lang/String;)Ljava/lang/StringBuilder;
     279: invokevirtual #75                 // Method java/lang/StringBuilder.toString:()Ljava/lang/String;
     282: invokevirtual #54                 // Method java/io/PrintStream.println:(Ljava/lang/String;)V
     285: goto          346
     288: iload         4
     290: istore        7
     292: aload_0
     293: aload_0
     294: arraylength
     295: iconst_1
     296: isub
     297: aaload
     298: iconst_0
     299: anewarray     #15                 // class java/lang/String
     302: invokestatic  #76                 // Method java/nio/file/Paths.get:(Ljava/lang/String;[Ljava/lang/String;)Ljava/nio/file/Path;
     305: astore        8
     307: aload         8
     309: new           #77                 // class io/sensesecure/clamav4j/ClamAV$1
     312: dup
     313: iload         7
     315: aload         6
     317: invokespecial #78                 // Method io/sensesecure/clamav4j/ClamAV$1."<init>":(ZLio/sensesecure/clamav4j/ClamAV;)V
     320: invokestatic  #79                 // Method java/nio/file/Files.walkFileTree:(Ljava/nio/file/Path;Ljava/nio/file/FileVisitor;)Ljava/nio/file/Path;
     323: pop
     324: goto          346
     327: astore        9
     329: ldc           #20                 // class io/sensesecure/clamav4j/ClamAV
     331: invokevirtual #27                 // Method java/lang/Class.getName:()Ljava/lang/String;
     334: invokestatic  #28                 // Method java/util/logging/Logger.getLogger:(Ljava/lang/String;)Ljava/util/logging/Logger;
     337: getstatic     #29                 // Field java/util/logging/Level.SEVERE:Ljava/util/logging/Level;
     340: aconst_null
     341: aload         9
     343: invokevirtual #30                 // Method java/util/logging/Logger.log:(Ljava/util/logging/Level;Ljava/lang/String;Ljava/lang/Throwable;)V
     346: return
    Exception table:
       from    to  target type
         307   324   327   Class java/io/IOException

  static {};
    Code:
       0: ldc           #80                 // String zINSTREAM\u0000
       2: invokevirtual #81                 // Method java/lang/String.getBytes:()[B
       5: putstatic     #31                 // Field INSTREAM:[B
       8: ldc           #82                 // String ^stream: (.+) FOUND$
      10: invokestatic  #83                 // Method java/util/regex/Pattern.compile:(Ljava/lang/String;)Ljava/util/regex/Pattern;
      13: putstatic     #40                 // Field FOUND:Ljava/util/regex/Pattern;
      16: ldc           #84                 // String zPING\u0000
      18: invokevirtual #81                 // Method java/lang/String.getBytes:()[B
      21: putstatic     #8                  // Field PING:[B
      24: ldc           #85                 // String zVERSION\u0000
      26: invokevirtual #81                 // Method java/lang/String.getBytes:()[B
      29: putstatic     #49                 // Field VERSION:[B
      32: return
}
